metamart_source_openlineage/__init__.py
metamart_source_openlineage/adapters.py
metamart_source_openlineage/base.py
metamart_source_openlineage/models.py
metamart_source_openlineage/package_definitions.py
metamart_source_openlineage/processor.py
metamart_source_openlineage/py.typed
metamart_source_openlineage/specs/__init__.py
metamart_source_openlineage/specs/facets/ColumnLineageDatasetFacet.json
metamart_source_openlineage/specs/facets/DataQualityAssertionsDatasetFacet.json
metamart_source_openlineage/specs/facets/DataQualityMetricsInputDatasetFacet.json
metamart_source_openlineage/specs/facets/DatasetVersionDatasetFacet.json
metamart_source_openlineage/specs/facets/DatasourceDatasetFacet.json
metamart_source_openlineage/specs/facets/DocumentationDatasetFacet.json
metamart_source_openlineage/specs/facets/DocumentationJobFacet.json
metamart_source_openlineage/specs/facets/ErrorMessageRunFacet.json
metamart_source_openlineage/specs/facets/ExternalQueryRunFacet.json
metamart_source_openlineage/specs/facets/ExtractionErrorRunFacet.json
metamart_source_openlineage/specs/facets/LifecycleStateChangeDatasetFacet.json
metamart_source_openlineage/specs/facets/NominalTimeRunFacet.json
metamart_source_openlineage/specs/facets/OutputStatisticsOutputDatasetFacet.json
metamart_source_openlineage/specs/facets/OwnershipDatasetFacet.json
metamart_source_openlineage/specs/facets/OwnershipJobFacet.json
metamart_source_openlineage/specs/facets/ParentRunFacet.json
metamart_source_openlineage/specs/facets/ProcessingEngineRunFacet.json
metamart_source_openlineage/specs/facets/SQLJobFacet.json
metamart_source_openlineage/specs/facets/SchemaDatasetFacet.json
metamart_source_openlineage/specs/facets/SourceCodeJobFacet.json
metamart_source_openlineage/specs/facets/SourceCodeLocationJobFacet.json
metamart_source_openlineage/specs/facets/StorageDatasetFacet.json
metamart_source_openlineage/specs/facets/SymlinksDatasetFacet.json
metamart_source_openlineage/specs/v1_0_0/__init__.py
metamart_source_openlineage-0.1.0a1.dist-info/METADATA
metamart_source_openlineage-0.1.0a1.dist-info/WHEEL
metamart_source_openlineage-0.1.0a1.dist-info/RECORD
